[
  {
    "id": "ark-recode-arktrist2ws0-1776909139626",
    "gameSlug": "ark-recode",
    "code": "ArkTrist2ws0",
    "description": "Ark Re:Code coupon",
    "descriptionEn": "Ark Re:Code coupon",
    "issuedDate": "2026-04-23",
    "expiryDate": null,
    "expired": false,
    "source": "other",
    "sourceUrl": "https://arca.live/b/codeark?category=%EC%BF%A0%ED%8F%B0"
  },
  {
    "id": "ark-recode-arkluciabear-1776909139626",
    "gameSlug": "ark-recode",
    "code": "ArkLuciaBear",
    "description": "Ark Re:Code coupon",
    "descriptionEn": "Ark Re:Code coupon",
    "issuedDate": "2026-04-23",
    "expiryDate": null,
    "expired": false,
    "source": "other",
    "sourceUrl": "https://arca.live/b/codeark?category=%EC%BF%A0%ED%8F%B0"
  },
  {
    "id": "ark-recode-ark2bartholo-1776909139626",
    "gameSlug": "ark-recode",
    "code": "Ark2Bartholo",
    "description": "Ark Re:Code coupon",
    "descriptionEn": "Ark Re:Code coupon",
    "issuedDate": "2026-04-23",
    "expiryDate": null,
    "expired": false,
    "source": "other",
    "sourceUrl": "https://arca.live/b/codeark?category=%EC%BF%A0%ED%8F%B0"
  },
  {
    "id": "ark-recode-arkxfangd2re-1776909139626",
    "gameSlug": "ark-recode",
    "code": "ArkxFangd2re",
    "description": "Ark Re:Code coupon",
    "descriptionEn": "Ark Re:Code coupon",
    "issuedDate": "2026-04-23",
    "expiryDate": null,
    "expired": false,
    "source": "other",
    "sourceUrl": "https://arca.live/b/codeark?category=%EC%BF%A0%ED%8F%B0"
  },
  {
    "id": "ark-recode-ark3kvxmesd9-1776909139627",
    "gameSlug": "ark-recode",
    "code": "Ark3kVXmesd9",
    "description": "Ark Re:Code coupon",
    "descriptionEn": "Ark Re:Code coupon",
    "issuedDate": "2026-04-23",
    "expiryDate": null,
    "expired": false,
    "source": "other",
    "sourceUrl": "https://arca.live/b/codeark?category=%EC%BF%A0%ED%8F%B0"
  },
  {
    "id": "ark-recode-ark20wjh26es-1776909139627",
    "gameSlug": "ark-recode",
    "code": "Ark20WJh26es",
    "description": "Ark Re:Code coupon",
    "descriptionEn": "Ark Re:Code coupon",
    "issuedDate": "2026-04-23",
    "expiryDate": null,
    "expired": false,
    "source": "other",
    "sourceUrl": "https://arca.live/b/codeark?category=%EC%BF%A0%ED%8F%B0"
  },
  {
    "id": "ark-recode-arks2026rtvw-1776909139627",
    "gameSlug": "ark-recode",
    "code": "ArkS2026Rtvw",
    "description": "Ark Re:Code coupon",
    "descriptionEn": "Ark Re:Code coupon",
    "issuedDate": "2026-04-23",
    "expiryDate": null,
    "expired": false,
    "source": "other",
    "sourceUrl": "https://arca.live/b/codeark?category=%EC%BF%A0%ED%8F%B0"
  },
  {
    "id": "ark-recode-ark20yjum26j-1776909139627",
    "gameSlug": "ark-recode",
    "code": "Ark20YjUm26J",
    "description": "Ark Re:Code coupon",
    "descriptionEn": "Ark Re:Code coupon",
    "issuedDate": "2026-04-23",
    "expiryDate": null,
    "expired": false,
    "source": "other",
    "sourceUrl": "https://arca.live/b/codeark?category=%EC%BF%A0%ED%8F%B0"
  },
  {
    "id": "ark-recode-arkd20w26dhn-1776909139627",
    "gameSlug": "ark-recode",
    "code": "Arkd20W26DHN",
    "description": "Ark Re:Code coupon",
    "descriptionEn": "Ark Re:Code coupon",
    "issuedDate": "2026-04-23",
    "expiryDate": null,
    "expired": false,
    "source": "other",
    "sourceUrl": "https://arca.live/b/codeark?category=%EC%BF%A0%ED%8F%B0"
  },
  {
    "id": "ark-recode-arkwc5vgf3df-1776909139627",
    "gameSlug": "ark-recode",
    "code": "ArkWc5vgf3df",
    "description": "Ark Re:Code coupon",
    "descriptionEn": "Ark Re:Code coupon",
    "issuedDate": "2026-04-23",
    "expiryDate": null,
    "expired": false,
    "source": "other",
    "sourceUrl": "https://arca.live/b/codeark?category=%EC%BF%A0%ED%8F%B0"
  },
  {
    "id": "cherrytale-ctkyh5dhkrky-1776909178101",
    "gameSlug": "cherrytale",
    "code": "CTkyH5DHKrKY",
    "description": "CherryTale coupon",
    "descriptionEn": "CherryTale coupon",
    "issuedDate": "2026-04-23",
    "expiryDate": null,
    "expired": false,
    "source": "other",
    "sourceUrl": "https://arca.live/b/cherrytale?category=%EC%BF%A0%ED%8F%B0"
  },
  {
    "id": "cherrytale-ctxuh3fnmxbr-1776909178101",
    "gameSlug": "cherrytale",
    "code": "CTXuH3fNMxbr",
    "description": "CherryTale coupon",
    "descriptionEn": "CherryTale coupon",
    "issuedDate": "2026-04-23",
    "expiryDate": null,
    "expired": false,
    "source": "other",
    "sourceUrl": "https://arca.live/b/cherrytale?category=%EC%BF%A0%ED%8F%B0"
  },
  {
    "id": "cherrytale-ctnq9buzs5wm-1776909178101",
    "gameSlug": "cherrytale",
    "code": "CTNq9buzs5wm",
    "description": "CherryTale coupon",
    "descriptionEn": "CherryTale coupon",
    "issuedDate": "2026-04-23",
    "expiryDate": null,
    "expired": false,
    "source": "other",
    "sourceUrl": "https://arca.live/b/cherrytale?category=%EC%BF%A0%ED%8F%B0"
  },
  {
    "id": "cherrytale-ctkdkjqkutvj-1776909178101",
    "gameSlug": "cherrytale",
    "code": "CTKDkjqKUtvJ",
    "description": "CherryTale coupon",
    "descriptionEn": "CherryTale coupon",
    "issuedDate": "2026-04-23",
    "expiryDate": null,
    "expired": false,
    "source": "other",
    "sourceUrl": "https://arca.live/b/cherrytale?category=%EC%BF%A0%ED%8F%B0"
  },
  {
    "id": "cherrytale-ct5hzdnueyyk-1776909178101",
    "gameSlug": "cherrytale",
    "code": "CT5hzdnueyyk",
    "description": "CherryTale coupon",
    "descriptionEn": "CherryTale coupon",
    "issuedDate": "2026-04-23",
    "expiryDate": null,
    "expired": false,
    "source": "other",
    "sourceUrl": "https://arca.live/b/cherrytale?category=%EC%BF%A0%ED%8F%B0"
  },
  {
    "id": "cherrytale-ctnv3k9tvymd-1776909178101",
    "gameSlug": "cherrytale",
    "code": "CTnv3K9tVyMD",
    "description": "CherryTale coupon",
    "descriptionEn": "CherryTale coupon",
    "issuedDate": "2026-04-23",
    "expiryDate": null,
    "expired": false,
    "source": "other",
    "sourceUrl": "https://arca.live/b/cherrytale?category=%EC%BF%A0%ED%8F%B0"
  },
  {
    "id": "cherrytale-ct9rgrn3x3an-1776909178101",
    "gameSlug": "cherrytale",
    "code": "CT9rgRn3X3an",
    "description": "CherryTale coupon",
    "descriptionEn": "CherryTale coupon",
    "issuedDate": "2026-04-23",
    "expiryDate": null,
    "expired": false,
    "source": "other",
    "sourceUrl": "https://arca.live/b/cherrytale?category=%EC%BF%A0%ED%8F%B0"
  },
  {
    "id": "cherrytale-ctjubxwyhwj3-1776909178101",
    "gameSlug": "cherrytale",
    "code": "CTJUbxwYHWj3",
    "description": "CherryTale coupon",
    "descriptionEn": "CherryTale coupon",
    "issuedDate": "2026-04-23",
    "expiryDate": null,
    "expired": false,
    "source": "other",
    "sourceUrl": "https://arca.live/b/cherrytale?category=%EC%BF%A0%ED%8F%B0"
  },
  {
    "id": "horizon-walker-horizonwalker2-1776909222613",
    "gameSlug": "horizon-walker",
    "code": "horizonwalker2",
    "description": "Horizon Walker coupon",
    "descriptionEn": "Horizon Walker coupon",
    "issuedDate": "2026-04-23",
    "expiryDate": null,
    "expired": false,
    "source": "other",
    "sourceUrl": "https://arca.live/b/horizonwalker2?target=all&keyword=%EC%BF%A0%ED%8F%B0&category=8"
  }
]
